mdx_math.py
python_markdown_math-0.8.dist-info/LICENSE
python_markdown_math-0.8.dist-info/METADATA
python_markdown_math-0.8.dist-info/WHEEL
python_markdown_math-0.8.dist-info/entry_points.txt
python_markdown_math-0.8.dist-info/top_level.txt
python_markdown_math-0.8.dist-info/RECORD
