Metadata-Version: 2.1
Name: python-markdown-math
Version: 0.8
Summary: Math extension for Python-Markdown
Home-page: https://github.com/mitya57/python-markdown-math
Author: Dmitry Shachnev
Author-email: mitya57@gmail.com
License: BSD 3-Clause License
Platform: UNKNOWN
Requires-Python: >=3.6
